mcp_cli_host/__init__.py
mcp_cli_host/console.py
mcp_cli_host/cmd/__init__.py
mcp_cli_host/cmd/app.py
mcp_cli_host/cmd/mcp.py
mcp_cli_host/cmd/stdio_client.py
mcp_cli_host/cmd/utils.py
mcp_cli_host/cmd/mcp_client_functions/__init__.py
mcp_cli_host/cmd/mcp_client_functions/elicitation_handler.py
mcp_cli_host/cmd/mcp_client_functions/err_monitor.py
mcp_cli_host/cmd/mcp_client_functions/notification_handler.py
mcp_cli_host/cmd/mcp_client_functions/roots_handler.py
mcp_cli_host/cmd/mcp_client_functions/sampling_handler.py
mcp_cli_host/llm/__init__.py
mcp_cli_host/llm/base_provider.py
mcp_cli_host/llm/models.py
mcp_cli_host/llm/azure/models.py
mcp_cli_host/llm/azure/provider.py
mcp_cli_host/llm/deepseek/provider.py
mcp_cli_host/llm/gemini/provider.py
mcp_cli_host/llm/ollama/models.py
mcp_cli_host/llm/ollama/provider.py
mcp_cli_host/llm/openai/provider.py
mcp_cli_host-0.1.13.dist-info/licenses/LICENSE
mcp_cli_host-0.1.13.dist-info/METADATA
mcp_cli_host-0.1.13.dist-info/WHEEL
mcp_cli_host-0.1.13.dist-info/entry_points.txt
mcp_cli_host-0.1.13.dist-info/top_level.txt
mcp_cli_host-0.1.13.dist-info/RECORD
