Metadata-Version: 2.4
Name: mcp-cli-host
Version: 0.1.13
Summary: Add your description here
Requires-Python: >=3.10
License-File: LICENSE
Requires-Dist: mcp[cli]>=1.12.0
Requires-Dist: ollama>=0.4.8
Requires-Dist: openai>=1.76.0
Requires-Dist: pydantic>=2.11.3
Requires-Dist: rich>=14.0.0
Requires-Dist: uritemplate>=4.2.0
Dynamic: license-file
